COPYING
COPYING.lesser
MANIFEST.in
NOTICE
README.md
requirements.txt
setup.py
compiler/__init__.py
compiler/api/__init__.py
compiler/api/compiler.py
compiler/api/source/auth_key.tl
compiler/api/source/main_api.tl
compiler/api/source/sys_msgs.tl
compiler/api/template/combinator.txt
compiler/api/template/type.txt
compiler/errors/__init__.py
compiler/errors/compiler.py
compiler/errors/sort.py
compiler/errors/source/303_SEE_OTHER.tsv
compiler/errors/source/400_BAD_REQUEST.tsv
compiler/errors/source/401_UNAUTHORIZED.tsv
compiler/errors/source/403_FORBIDDEN.tsv
compiler/errors/source/406_NOT_ACCEPTABLE.tsv
compiler/errors/source/420_FLOOD.tsv
compiler/errors/source/500_INTERNAL_SERVER_ERROR.tsv
compiler/errors/source/503_SERVICE_UNAVAILABLE.tsv
compiler/errors/template/class.txt
compiler/errors/template/sub_class.txt
maling.egg-info/PKG-INFO
maling.egg-info/SOURCES.txt
maling.egg-info/dependency_links.txt
maling.egg-info/not-zip-safe
maling.egg-info/requires.txt
maling.egg-info/top_level.txt
team/__init__.py
team/client.py
team/dispatcher.py
team/emoji.py
team/file_id.py
team/filters.py
team/mime_types.py
team/py.typed
team/sync.py
team/utils.py
team/connection/__init__.py
team/connection/connection.py
team/connection/transport/__init__.py
team/connection/transport/tcp/__init__.py
team/connection/transport/tcp/tcp.py
team/connection/transport/tcp/tcp_abridged.py
team/connection/transport/tcp/tcp_abridged_o.py
team/connection/transport/tcp/tcp_full.py
team/connection/transport/tcp/tcp_intermediate.py
team/connection/transport/tcp/tcp_intermediate_o.py
team/crypto/__init__.py
team/crypto/aes.py
team/crypto/mtproto.py
team/crypto/prime.py
team/crypto/rsa.py
team/enums/__init__.py
team/enums/auto_name.py
team/enums/chat_action.py
team/enums/chat_event_action.py
team/enums/chat_member_status.py
team/enums/chat_members_filter.py
team/enums/chat_type.py
team/enums/message_entity_type.py
team/enums/message_media_type.py
team/enums/message_service_type.py
team/enums/messages_filter.py
team/enums/next_code_type.py
team/enums/parse_mode.py
team/enums/poll_type.py
team/enums/sent_code_type.py
team/enums/user_status.py
team/errors/__init__.py
